<?xml version="1.0" encoding="UTF-8"?>
	<mbm>
		<head>000000004d53473200000100</head>
		<size>f80b0000</size>
		<number>90010000</number>
		<j>200000000000000000000000</j>
		<body>
			<id id="0">
				<origin>\f859\\0300\\f81b\\565f\\4348\\4152\\5f31\\3032\\2f45\\5645\\4e54\\2f62\\6172\\5f32\\3137\\0000\やあ、その依頼だね。\f801\それはマギニア司令部からのものだよ。\f801\\ffff\</origin>
				<translate>\f859\\0300\\f81b\\565f\\4348\\4152\\5f31\\3032\\2f45\\5645\\4e54\\2f62\\6172\\5f32\\3137\\0000\やあ、その依頼だね。\f801\それはマギニア司令部からのものだよ。\f801\\ffff\</translate>
			</id>
			<id id="1">
				<origin>\f859\\0300\そう言えば、以前のワイバーンを倒したの\f801\君たちなんだって？\f801\だったら適任かもね！\f801\\ffff\</origin>
				<translate>\f859\\0300\そう言えば、以前のワイバーンを倒したの\f801\君たちなんだって？\f801\だったら適任かもね！\f801\\ffff\</translate>
			</id>
			<id id="2">
				<origin>\f859\\0300\\f81b\\565f\\4348\\4152\\5f31\\3032\\2f45\\5645\\4e54\\2f62\\6172\\5f32\\3235\\0000\依頼書にもある通り、ワイバーンたちが\f801\レムリア各地から出現したらしいんだ。\f801\\f802\お蔭でレムリア各地に出かけていた人が\f801\帰れず困ってるんだってさ。\f801\\ffff\</origin>
				<translate>\f859\\0300\\f81b\\565f\\4348\\4152\\5f31\\3032\\2f45\\5645\\4e54\\2f62\\6172\\5f32\\3235\\0000\依頼書にもある通り、ワイバーンたちが\f801\レムリア各地から出現したらしいんだ。\f801\\f802\お蔭でレムリア各地に出かけていた人が\f801\帰れず困ってるんだってさ。\f801\\ffff\</translate>
			</id>
			<id id="3"/>
			<id id="4">
				<origin>\f859\\0300\\f81b\\565f\\4348\\4152\\5f31\\3032\\2f53\\5953\\5445\\4d2f\\4558\\4954\\315f\\4e4f\\524d\\414c\\2f62\\6172\\5f30\\3230\\0000\街の外に救助を行う衛兵さんたちが\f801\待っているらしいから、直接会って\f801\話を聞いてみてよ！\f801\\ffff\</origin>
				<translate>\f859\\0300\\f81b\\565f\\4348\\4152\\5f31\\3032\\2f53\\5953\\5445\\4d2f\\4558\\4954\\315f\\4e4f\\524d\\414c\\2f62\\6172\\5f30\\3230\\0000\街の外に救助を行う衛兵さんたちが\f801\待っているらしいから、直接会って\f801\話を聞いてみてよ！\f801\\ffff\</translate>
			</id>
			<id id="5"/>
			<id id="6"/>
			<id id="7"/>
			<id id="8"/>
			<id id="9"/>
			<id id="10"/>
			<id id="11"/>
			<id id="12"/>
			<id id="13"/>
			<id id="14"/>
			<id id="15"/>
			<id id="16"/>
			<id id="17"/>
			<id id="18"/>
			<id id="19"/>
			<id id="20"/>
			<id id="21"/>
			<id id="22"/>
			<id id="23"/>
			<id id="24"/>
			<id id="25"/>
			<id id="26"/>
			<id id="27"/>
			<id id="28"/>
			<id id="29"/>
			<id id="30"/>
			<id id="31"/>
			<id id="32"/>
			<id id="33"/>
			<id id="34"/>
			<id id="35"/>
			<id id="36"/>
			<id id="37"/>
			<id id="38"/>
			<id id="39"/>
			<id id="40"/>
			<id id="41"/>
			<id id="42"/>
			<id id="43"/>
			<id id="44"/>
			<id id="45"/>
			<id id="46"/>
			<id id="47"/>
			<id id="48"/>
			<id id="49"/>
			<id id="50">
				<origin>\f859\\0300\\f81b\\565f\\4348\\4152\\5f31\\3032\\2f45\\5645\\4e54\\2f62\\6172\\5f32\\3034\\0000\いやぁ、お疲れお疲れ。\f801\やっぱり君たちはやってくれると思ったよ。\f801\……ね？ 楽勝だったでしょ？\f801\\ffff\</origin>
				<translate>\f859\\0300\\f81b\\565f\\4348\\4152\\5f31\\3032\\2f45\\5645\\4e54\\2f62\\6172\\5f32\\3034\\0000\いやぁ、お疲れお疲れ。\f801\やっぱり君たちはやってくれると思ったよ。\f801\……ね？ 楽勝だったでしょ？\f801\\ffff\</translate>
			</id>
			<id id="51"/>
			<id id="52">
				<origin>\f859\\0300\\f81b\\565f\\4348\\4152\\5f31\\3032\\2f45\\5645\\4e54\\2f62\\6172\\5f32\\3436\\0000\でも飛竜が大量発生なんて\f801\どうしたんだろうね。\f801\\ffff\</origin>
				<translate>\f859\\0300\\f81b\\565f\\4348\\4152\\5f31\\3032\\2f45\\5645\\4e54\\2f62\\6172\\5f32\\3436\\0000\でも飛竜が大量発生なんて\f801\どうしたんだろうね。\f801\\ffff\</translate>
			</id>
			<id id="53">
				<origin>\f859\\0300\\f81b\\565f\\4348\\4152\\5f31\\3032\\2f45\\5645\\4e54\\2f62\\6172\\5f32\\3337\\0000\ま、考えても仕方ないよね？\f801\はい、これが今回の報酬だよ。\f801\お疲れちゃんでした！\f801\\ffff\</origin>
				<translate>\f859\\0300\\f81b\\565f\\4348\\4152\\5f31\\3032\\2f45\\5645\\4e54\\2f62\\6172\\5f32\\3337\\0000\ま、考えても仕方ないよね？\f801\はい、これが今回の報酬だよ。\f801\お疲れちゃんでした！\f801\\ffff\</translate>
			</id>
			<id id="54"/>
			<id id="55"/>
			<id id="56"/>
			<id id="57"/>
			<id id="58"/>
			<id id="59"/>
			<id id="60"/>
			<id id="61"/>
			<id id="62"/>
			<id id="63"/>
			<id id="64"/>
			<id id="65"/>
			<id id="66"/>
			<id id="67"/>
			<id id="68"/>
			<id id="69"/>
			<id id="70"/>
			<id id="71"/>
			<id id="72"/>
			<id id="73"/>
			<id id="74"/>
			<id id="75"/>
			<id id="76"/>
			<id id="77"/>
			<id id="78"/>
			<id id="79"/>
			<id id="80"/>
			<id id="81"/>
			<id id="82"/>
			<id id="83"/>
			<id id="84"/>
			<id id="85"/>
			<id id="86"/>
			<id id="87"/>
			<id id="88"/>
			<id id="89"/>
			<id id="90"/>
			<id id="91"/>
			<id id="92"/>
			<id id="93"/>
			<id id="94"/>
			<id id="95"/>
			<id id="96"/>
			<id id="97"/>
			<id id="98"/>
			<id id="99"/>
			<id id="100">
				<origin>マギニアの外にいる衛兵に話を聞け！\f801\\ffff\</origin>
				<translate>マギニアの外にいる衛兵に話を聞け！\f801\\ffff\</translate>
			</id>
			<id id="101">
				<origin>各地で逃げ遅れた人に\f801\\f804\\0500\飛竜避けの笛\f804\\0000\を届けろ！\f801\\ffff\</origin>
				<translate>各地で逃げ遅れた人に\f801\\f804\\0500\飛竜避けの笛\f804\\0000\を届けろ！\f801\\ffff\</translate>
			</id>
			<id id="102"/>
			<id id="103">
				<origin>全ての遭難者に笛を届けた。\f801\酒場に報告に行こう。\f801\\ffff\</origin>
				<translate>全ての遭難者に笛を届けた。\f801\酒場に報告に行こう。\f801\\ffff\</translate>
			</id>
			<id id="104"/>
			<id id="105"/>
			<id id="106"/>
			<id id="107"/>
			<id id="108"/>
			<id id="109"/>
			<id id="110"/>
			<id id="111"/>
			<id id="112"/>
			<id id="113"/>
			<id id="114"/>
			<id id="115"/>
			<id id="116"/>
			<id id="117"/>
			<id id="118"/>
			<id id="119"/>
			<id id="120"/>
			<id id="121"/>
			<id id="122"/>
			<id id="123"/>
			<id id="124"/>
			<id id="125"/>
			<id id="126"/>
			<id id="127"/>
			<id id="128"/>
			<id id="129"/>
			<id id="130"/>
			<id id="131"/>
			<id id="132"/>
			<id id="133"/>
			<id id="134"/>
			<id id="135"/>
			<id id="136"/>
			<id id="137"/>
			<id id="138"/>
			<id id="139"/>
			<id id="140"/>
			<id id="141"/>
			<id id="142"/>
			<id id="143"/>
			<id id="144"/>
			<id id="145"/>
			<id id="146"/>
			<id id="147"/>
			<id id="148"/>
			<id id="149"/>
			<id id="150">
				<origin>君たちがマギニアを出ると\f801\衛兵たちが駆け寄ってくる。\f801\\ffff\</origin>
				<translate>君たちがマギニアを出ると\f801\衛兵たちが駆け寄ってくる。\f801\\ffff\</translate>
			</id>
			<id id="151"/>
			<id id="152"/>
			<id id="153">
				<origin>\f859\\0700\「君たちがクエストを引き受けてくれた\f801\冒険者か？ よろしく頼むぞ！」\f801\\f802\「司令部の調査では、飛竜たちは\f801\ある特定の音が苦手だと判明したのだ」\f801\\f802\「そこでその音を出す飛竜避けの笛を\f801\戻れずにいる者たちに届けてもらいたい」\f801\\ffff\</origin>
				<translate>\f859\\0700\「君たちがクエストを引き受けてくれた\f801\冒険者か？ よろしく頼むぞ！」\f801\\f802\「司令部の調査では、飛竜たちは\f801\ある特定の音が苦手だと判明したのだ」\f801\\f802\「そこでその音を出す飛竜避けの笛を\f801\戻れずにいる者たちに届けてもらいたい」\f801\\ffff\</translate>
			</id>
			<id id="154"/>
			<id id="155"/>
			<id id="156">
				<origin>\f859\\0700\「我々が把握している遭難者たちは\f801\この辺りにいる。すまないが頼んだぞ」\f801\\ffff\</origin>
				<translate>\f859\\0700\「我々が把握している遭難者たちは\f801\この辺りにいる。すまないが頼んだぞ」\f801\\ffff\</translate>
			</id>
			<id id="157"/>
			<id id="158"/>
			<id id="159">
				<origin>衛兵たちは遭難者の場所を伝えると\f801\荷物をまとめ立ち去っていく。\f801\彼らも別の現場に向かうのだろう。\f801\\f802\君たちは指定された場所へ向かい\f801\救助活動を行うことにする。\f801\\ffff\</origin>
				<translate>衛兵たちは遭難者の場所を伝えると\f801\荷物をまとめ立ち去っていく。\f801\彼らも別の現場に向かうのだろう。\f801\\f802\君たちは指定された場所へ向かい\f801\救助活動を行うことにする。\f801\\ffff\</translate>
			</id>
			<id id="160"/>
			<id id="161"/>
			<id id="162"/>
			<id id="163"/>
			<id id="164"/>
			<id id="165"/>
			<id id="166"/>
			<id id="167"/>
			<id id="168"/>
			<id id="169"/>
			<id id="170"/>
			<id id="171"/>
			<id id="172"/>
			<id id="173"/>
			<id id="174"/>
			<id id="175"/>
			<id id="176"/>
			<id id="177"/>
			<id id="178"/>
			<id id="179"/>
			<id id="180"/>
			<id id="181"/>
			<id id="182"/>
			<id id="183"/>
			<id id="184"/>
			<id id="185"/>
			<id id="186"/>
			<id id="187"/>
			<id id="188"/>
			<id id="189"/>
			<id id="190"/>
			<id id="191"/>
			<id id="192"/>
			<id id="193"/>
			<id id="194"/>
			<id id="195"/>
			<id id="196"/>
			<id id="197"/>
			<id id="198"/>
			<id id="199"/>
			<id id="200"/>
			<id id="201"/>
			<id id="202"/>
			<id id="203"/>
			<id id="204"/>
			<id id="205"/>
			<id id="206"/>
			<id id="207"/>
			<id id="208"/>
			<id id="209"/>
			<id id="210"/>
			<id id="211"/>
			<id id="212"/>
			<id id="213"/>
			<id id="214"/>
			<id id="215"/>
			<id id="216"/>
			<id id="217"/>
			<id id="218"/>
			<id id="219"/>
			<id id="220"/>
			<id id="221"/>
			<id id="222"/>
			<id id="223"/>
			<id id="224"/>
			<id id="225"/>
			<id id="226"/>
			<id id="227"/>
			<id id="228"/>
			<id id="229"/>
			<id id="230"/>
			<id id="231"/>
			<id id="232"/>
			<id id="233"/>
			<id id="234"/>
			<id id="235"/>
			<id id="236"/>
			<id id="237"/>
			<id id="238"/>
			<id id="239"/>
			<id id="240"/>
			<id id="241"/>
			<id id="242"/>
			<id id="243"/>
			<id id="244"/>
			<id id="245"/>
			<id id="246"/>
			<id id="247"/>
			<id id="248"/>
			<id id="249"/>
			<id id="250"/>
			<id id="251"/>
			<id id="252"/>
			<id id="253"/>
			<id id="254"/>
			<id id="255"/>
			<id id="256"/>
			<id id="257"/>
			<id id="258"/>
			<id id="259"/>
			<id id="260"/>
			<id id="261"/>
			<id id="262"/>
			<id id="263"/>
			<id id="264"/>
			<id id="265"/>
			<id id="266"/>
			<id id="267"/>
			<id id="268"/>
			<id id="269"/>
			<id id="270"/>
			<id id="271"/>
			<id id="272"/>
			<id id="273"/>
			<id id="274"/>
			<id id="275"/>
			<id id="276"/>
			<id id="277"/>
			<id id="278"/>
			<id id="279"/>
			<id id="280"/>
			<id id="281"/>
			<id id="282"/>
			<id id="283"/>
			<id id="284"/>
			<id id="285"/>
			<id id="286"/>
			<id id="287"/>
			<id id="288"/>
			<id id="289"/>
			<id id="290"/>
			<id id="291"/>
			<id id="292"/>
			<id id="293"/>
			<id id="294"/>
			<id id="295"/>
			<id id="296"/>
			<id id="297"/>
			<id id="298"/>
			<id id="299"/>
			<id id="300"/>
			<id id="301"/>
			<id id="302"/>
			<id id="303"/>
			<id id="304"/>
			<id id="305"/>
			<id id="306"/>
			<id id="307"/>
			<id id="308"/>
			<id id="309"/>
			<id id="310"/>
			<id id="311"/>
			<id id="312"/>
			<id id="313"/>
			<id id="314"/>
			<id id="315"/>
			<id id="316"/>
			<id id="317"/>
			<id id="318"/>
			<id id="319"/>
			<id id="320"/>
			<id id="321"/>
			<id id="322"/>
			<id id="323"/>
			<id id="324"/>
			<id id="325"/>
			<id id="326"/>
			<id id="327"/>
			<id id="328"/>
			<id id="329"/>
			<id id="330"/>
			<id id="331"/>
			<id id="332"/>
			<id id="333"/>
			<id id="334"/>
			<id id="335"/>
			<id id="336"/>
			<id id="337"/>
			<id id="338"/>
			<id id="339"/>
			<id id="340"/>
			<id id="341"/>
			<id id="342"/>
			<id id="343"/>
			<id id="344"/>
			<id id="345"/>
			<id id="346"/>
			<id id="347"/>
			<id id="348"/>
			<id id="349"/>
			<id id="350">
				<origin>洞窟に足を踏み入れた君たちは\f801\すぐ目の前で仁王立ちしたパンダと\f801\睨み合う飛竜を発見する！\f801\\f802\見ればパンダの毛皮のあちこちは\f801\血に染まり、飛竜もまたケガを\f801\負っているようだ…。\f801\\ffff\</origin>
				<translate>洞窟に足を踏み入れた君たちは\f801\すぐ目の前で仁王立ちしたパンダと\f801\睨み合う飛竜を発見する！\f801\\f802\見ればパンダの毛皮のあちこちは\f801\血に染まり、飛竜もまたケガを\f801\負っているようだ…。\f801\\ffff\</translate>
			</id>
			<id id="351"/>
			<id id="352"/>
			<id id="353">
				<origin>\f859\\0900\「ランラン！！」\f801\\ffff\</origin>
				<translate>\f859\\0900\「ランラン！！」\f801\\ffff\</translate>
			</id>
			<id id="354"/>
			<id id="355"/>
			<id id="356">
				<origin>君たちの背後から様子を見ていた\f801\ビルギッタが大きな声でそう呼ぶと\f801\パンダが振り向いて笑顔になる。\f801\\ffff\</origin>
				<translate>君たちの背後から様子を見ていた\f801\ビルギッタが大きな声でそう呼ぶと\f801\パンダが振り向いて笑顔になる。\f801\\ffff\</translate>
			</id>
			<id id="357">
				<origin>どうやらこのパンダが\f801\ビルギッタのお父さんのような\f801\存在らしい。\f801\\ffff\</origin>
				<translate>どうやらこのパンダが\f801\ビルギッタのお父さんのような\f801\存在らしい。\f801\\ffff\</translate>
			</id>
			<id id="358">
				<origin>君たちはランランを庇い\f801\飛竜に挑もうとした時…\f801\\f802\不意に\f843\\0000\が\f801\笛を取り出して口にする！\f801\\f802\けたたましい音が響き渡ると\f801\飛竜は驚いてその場から空へ消える。\f801\飛竜避けの笛が見事効果を発したのだ！\f801\\ffff\</origin>
				<translate>君たちはランランを庇い\f801\飛竜に挑もうとした時…\f801\\f802\不意に\f843\\0000\が\f801\笛を取り出して口にする！\f801\\f802\けたたましい音が響き渡ると\f801\飛竜は驚いてその場から空へ消える。\f801\飛竜避けの笛が見事効果を発したのだ！\f801\\ffff\</translate>
			</id>
			<id id="359">
				<origin>飛竜を撃退した君たちに\f801\ビルギッタが歩み寄って頭を下げる。\f801\\ffff\</origin>
				<translate>飛竜を撃退した君たちに\f801\ビルギッタが歩み寄って頭を下げる。\f801\\ffff\</translate>
			</id>
			<id id="360">
				<origin>\f859\\0900\\f81b\\565f\\4348\\4152\\5f31\\3930\\2f45\\5645\\4e54\\2f62\\6972\\5f32\\3236\\0000\「み、みなさん。\f801\今度もまたありがとうございました」\f801\\f802\「ランランも無事に助かって…\f801\ホントによかったです」\f801\\ffff\</origin>
				<translate>\f859\\0900\\f81b\\565f\\4348\\4152\\5f31\\3930\\2f45\\5645\\4e54\\2f62\\6972\\5f32\\3236\\0000\「み、みなさん。\f801\今度もまたありがとうございました」\f801\\f802\「ランランも無事に助かって…\f801\ホントによかったです」\f801\\ffff\</translate>
			</id>
			<id id="361"/>
			<id id="362">
				<origin>涙目でそう告げるビルギッタに\f801\君たちは飛竜避けの笛を手渡す。\f801\\ffff\</origin>
				<translate>涙目でそう告げるビルギッタに\f801\君たちは飛竜避けの笛を手渡す。\f801\\ffff\</translate>
			</id>
			<id id="363"/>
			<id id="364"/>
			<id id="365">
				<origin>\f859\\0900\「これで…安全に帰れるのですね」\f801\\ffff\</origin>
				<translate>\f859\\0900\「これで…安全に帰れるのですね」\f801\\ffff\</translate>
			</id>
			<id id="366"/>
			<id id="367"/>
			<id id="368">
				<origin>ありがとうございます、と頭を下げると\f801\ランランとビルギッタは帰っていく。\f801\\ffff\</origin>
				<translate>ありがとうございます、と頭を下げると\f801\ランランとビルギッタは帰っていく。\f801\\ffff\</translate>
			</id>
			<id id="369">
				<origin>君たちは次の遭難者を救うため\f801\地図へと視線を向ける。\f801\\ffff\</origin>
				<translate>君たちは次の遭難者を救うため\f801\地図へと視線を向ける。\f801\\ffff\</translate>
			</id>
			<id id="370"/>
			<id id="371"/>
			<id id="372"/>
			<id id="373"/>
			<id id="374"/>
			<id id="375"/>
			<id id="376"/>
			<id id="377"/>
			<id id="378"/>
			<id id="379"/>
			<id id="380"/>
			<id id="381"/>
			<id id="382"/>
			<id id="383"/>
			<id id="384"/>
			<id id="385"/>
			<id id="386"/>
			<id id="387"/>
			<id id="388"/>
			<id id="389"/>
			<id id="390"/>
			<id id="391"/>
			<id id="392"/>
			<id id="393"/>
			<id id="394"/>
			<id id="395"/>
			<id id="396"/>
			<id id="397"/>
			<id id="398"/>
			<id id="399"/>
			<id id="400">
				<origin>これで依頼されていた全ての\f801\遭難者へ笛を届けることができた！\f801\\f802\依頼の達成を報告するため\f801\酒場に戻るといいだろう。\f801\\ffff\</origin>
				<translate>これで依頼されていた全ての\f801\遭難者へ笛を届けることができた！\f801\\f802\依頼の達成を報告するため\f801\酒場に戻るといいだろう。\f801\\ffff\</translate>
			</id>
		</body>
	</mbm>
